[{"body":"","link":"https://vuduynhien.com/vi/post/","section":"post","tags":null,"title":"Posts"},{"body":"","link":"https://vuduynhien.com/vi/","section":"","tags":null,"title":"Vũ Duy Nhiên Blog"},{"body":"Vũ Duy Nhiên là một sinh viên.\n","link":"https://vuduynhien.com/vi/about/","section":"","tags":null,"title":"Về Vũ Duy Nhiên"},{"body":"","link":"https://vuduynhien.com/vi/post/vi/warn/","section":"post","tags":null,"title":"Ê qua en đọc đi, bên vi không có bài viết đâu"},{"body":"","link":"https://vuduynhien.com/vi/categories/","section":"categories","tags":null,"title":"Categories"},{"body":"","link":"https://vuduynhien.com/vi/series/","section":"series","tags":null,"title":"Series"},{"body":"","link":"https://vuduynhien.com/vi/tags/","section":"tags","tags":null,"title":"Tags"}]